odoo/addons/partner_middlename/README.rst
odoo/addons/partner_middlename/__init__.py
odoo/addons/partner_middlename/__manifest__.py
odoo/addons/partner_middlename/i18n/it.po
odoo/addons/partner_middlename/i18n/partner_middlename.pot
odoo/addons/partner_middlename/models/__init__.py
odoo/addons/partner_middlename/models/res_config_settings.py
odoo/addons/partner_middlename/models/res_partner.py
odoo/addons/partner_middlename/readme/CONFIGURE.rst
odoo/addons/partner_middlename/readme/CONTRIBUTORS.rst
odoo/addons/partner_middlename/readme/DESCRIPTION.rst
odoo/addons/partner_middlename/readme/USAGE.rst
odoo/addons/partner_middlename/static/description/icon.png
odoo/addons/partner_middlename/static/description/index.html
odoo/addons/partner_middlename/tests/__init__.py
odoo/addons/partner_middlename/tests/test_config.py
odoo/addons/partner_middlename/tests/test_name.py
odoo/addons/partner_middlename/views/res_partner.xml
odoo/addons/partner_middlename/views/res_user.xml
odoo_addon_partner_middlename-16.0.1.0.0.7.dist-info/METADATA
odoo_addon_partner_middlename-16.0.1.0.0.7.dist-info/WHEEL
odoo_addon_partner_middlename-16.0.1.0.0.7.dist-info/top_level.txt
odoo_addon_partner_middlename-16.0.1.0.0.7.dist-info/RECORD
